thingspire_auto_ml/__init__.py
thingspire_auto_ml/hyperparameter_optimization.py
thingspire_auto_ml/owtestandscore.py
thingspire_auto_ml/icons/number.svg
thingspire_auto_ml/icons/plus.svg
thingspire_auto_ml/icons/print.svg
thingspire_auto_ml-0.0.4.dist-info/LICENSE
thingspire_auto_ml-0.0.4.dist-info/METADATA
thingspire_auto_ml-0.0.4.dist-info/WHEEL
thingspire_auto_ml-0.0.4.dist-info/entry_points.txt
thingspire_auto_ml-0.0.4.dist-info/top_level.txt
thingspire_auto_ml-0.0.4.dist-info/RECORD
