Metadata-Version: 2.1
Name: thingspire-auto-ml
Version: 0.0.4
Summary: Random Forest Optimization
Home-page: https://github.com/jmani0223/plus_pkg.git
Author: jmani
Author-email: jmani0223@gmail.com
License: UNKNOWN
Platform: UNKNOWN
Classifier: Programming Language :: Python :: 3
Classifier: License :: OSI Approved :: MIT License
Classifier: Operating System :: OS Independent
